{
  "started_at": "2026-02-15T14:55:25.177222Z",
  "finished_at": "2026-02-15T14:55:26.276965Z",
  "status": "no_candidates",
  "message": "no mispricing candidates above threshold",
  "selected_markets": [
    {
      "ticker": "KXDOTD-26FEB1510-T0.79999",
      "title": "Polkdadot price  on Feb 15, 2026?",
      "yes_bid_cents": 0.0,
      "yes_ask_cents": 0.0,
      "volume": 0.0
    },
    {
      "ticker": "KXXRPD-26FEB1510-T2.09999",
      "title": "Ripple price  on Feb 15, 2026?",
      "yes_bid_cents": 0.0,
      "yes_ask_cents": 0.0,
      "volume": 0.0
    },
    {
      "ticker": "KXXLMD-26FEB1510-T-0.2600001",
      "title": "XLM price  on Feb 15, 2026?",
      "yes_bid_cents": 0.0,
      "yes_ask_cents": 0.0,
      "volume": 0.0
    },
    {
      "ticker": "KXDOTD-26FEB1510-T1.79999",
      "title": "Polkdadot price  on Feb 15, 2026?",
      "yes_bid_cents": 0.0,
      "yes_ask_cents": 0.0,
      "volume": 0.0
    },
    {
      "ticker": "KXLTC-26FEB1510-B67.5",
      "title": "Litecoin price range  on Feb 15, 2026?",
      "yes_bid_cents": 0.0,
      "yes_ask_cents": 0.0,
      "volume": 0.0
    },
    {
      "ticker": "KXXLMD-26FEB1510-T-0.1600001",
      "title": "XLM price  on Feb 15, 2026?",
      "yes_bid_cents": 0.0,
      "yes_ask_cents": 0.0,
      "volume": 0.0
    },
    {
      "ticker": "KXXRPD-26FEB1510-T1.17999",
      "title": "Ripple price  on Feb 15, 2026?",
      "yes_bid_cents": 0.0,
      "yes_ask_cents": 0.0,
      "volume": 0.0
    },
    {
      "ticker": "KXDOTD-26FEB1510-T0.19999",
      "title": "Polkdadot price  on Feb 15, 2026?",
      "yes_bid_cents": 0.0,
      "yes_ask_cents": 0.0,
      "volume": 0.0
    },
    {
      "ticker": "KXXLMD-26FEB1510-T-0.0400001",
      "title": "XLM price  on Feb 15, 2026?",
      "yes_bid_cents": 0.0,
      "yes_ask_cents": 0.0,
      "volume": 0.0
    },
    {
      "ticker": "KXDOTD-26FEB1510-T-0.50001",
      "title": "Polkdadot price  on Feb 15, 2026?",
      "yes_bid_cents": 0.0,
      "yes_ask_cents": 0.0,
      "volume": 0.0
    },
    {
      "ticker": "KXLINKD-26FEB1510-T5.59999",
      "title": "Chainlink price  on Feb 15, 2026?",
      "yes_bid_cents": 0.0,
      "yes_ask_cents": 0.0,
      "volume": 0.0
    },
    {
      "ticker": "KXDOT-26FEB1510-B-1.65",
      "title": "Polkdadot price  on Feb 15, 2026?",
      "yes_bid_cents": 0.0,
      "yes_ask_cents": 0.0,
      "volume": 0.0
    },
    {
      "ticker": "KXXLMD-26FEB1510-T-0.0100001",
      "title": "XLM price  on Feb 15, 2026?",
      "yes_bid_cents": 0.0,
      "yes_ask_cents": 0.0,
      "volume": 0.0
    },
    {
      "ticker": "KXXLMD-26FEB1510-T0.0699999",
      "title": "XLM price  on Feb 15, 2026?",
      "yes_bid_cents": 0.0,
      "yes_ask_cents": 0.0,
      "volume": 0.0
    },
    {
      "ticker": "KXLTCD-26FEB1510-T82.9999",
      "title": "Litecoin price  on Feb 15, 2026?",
      "yes_bid_cents": 0.0,
      "yes_ask_cents": 0.0,
      "volume": 0.0
    },
    {
      "ticker": "KXXRPD-26FEB1510-T1.47999",
      "title": "Ripple price  on Feb 15, 2026?",
      "yes_bid_cents": 0.0,
      "yes_ask_cents": 0.0,
      "volume": 0.0
    },
    {
      "ticker": "KXLTCD-26FEB1510-T68.9999",
      "title": "Litecoin price  on Feb 15, 2026?",
      "yes_bid_cents": 0.0,
      "yes_ask_cents": 0.0,
      "volume": 0.0
    },
    {
      "ticker": "KXDOTD-26FEB1510-T-1.60001",
      "title": "Polkdadot price  on Feb 15, 2026?",
      "yes_bid_cents": 0.0,
      "yes_ask_cents": 0.0,
      "volume": 0.0
    },
    {
      "ticker": "KXLINKD-26FEB1510-T5.19999",
      "title": "Chainlink price  on Feb 15, 2026?",
      "yes_bid_cents": 0.0,
      "yes_ask_cents": 0.0,
      "volume": 0.0
    },
    {
      "ticker": "KXAVAXD-26FEB1510-T8.9999",
      "title": "Avalanche price  on Feb 15, 2026?",
      "yes_bid_cents": 0.0,
      "yes_ask_cents": 0.0,
      "volume": 0.0
    },
    {
      "ticker": "KXBCHD-26FEB1510-T459.999",
      "title": "Bitcoin Cash price  on Feb 15, 2026?",
      "yes_bid_cents": 0.0,
      "yes_ask_cents": 0.0,
      "volume": 0.0
    },
    {
      "ticker": "KXDOT-26FEB1510-B-0.15",
      "title": "Polkdadot price  on Feb 15, 2026?",
      "yes_bid_cents": 0.0,
      "yes_ask_cents": 0.0,
      "volume": 0.0
    },
    {
      "ticker": "KXXLMD-26FEB1510-T0.3899999",
      "title": "XLM price  on Feb 15, 2026?",
      "yes_bid_cents": 0.0,
      "yes_ask_cents": 0.0,
      "volume": 0.0
    },
    {
      "ticker": "KXXRP-26FEB1510-B0.870",
      "title": "Ripple price  on Feb 15, 2026?",
      "yes_bid_cents": 0.0,
      "yes_ask_cents": 0.0,
      "volume": 0.0
    },
    {
      "ticker": "KXLTCD-26FEB1510-T78.9999",
      "title": "Litecoin price  on Feb 15, 2026?",
      "yes_bid_cents": 0.0,
      "yes_ask_cents": 0.0,
      "volume": 0.0
    },
    {
      "ticker": "KXXLMD-26FEB1510-T-0.1200001",
      "title": "XLM price  on Feb 15, 2026?",
      "yes_bid_cents": 0.0,
      "yes_ask_cents": 0.0,
      "volume": 0.0
    },
    {
      "ticker": "KXLTC-26FEB1510-B39.5",
      "title": "Litecoin price range  on Feb 15, 2026?",
      "yes_bid_cents": 0.0,
      "yes_ask_cents": 0.0,
      "volume": 0.0
    },
    {
      "ticker": "KXXLM-26FEB1510-B0.4450000",
      "title": "XLM price  on Feb 15, 2026?",
      "yes_bid_cents": 0.0,
      "yes_ask_cents": 0.0,
      "volume": 0.0
    },
    {
      "ticker": "KXLTCD-26FEB1510-T44.9999",
      "title": "Litecoin price  on Feb 15, 2026?",
      "yes_bid_cents": 0.0,
      "yes_ask_cents": 0.0,
      "volume": 0.0
    },
    {
      "ticker": "KXAVAX-26FEB1510-B4.25",
      "title": "Avalanche price range  on Feb 15, 2026?",
      "yes_bid_cents": 0.0,
      "yes_ask_cents": 0.0,
      "volume": 0.0
    },
    {
      "ticker": "KXLTCD-26FEB1510-T41.9999",
      "title": "Litecoin price  on Feb 15, 2026?",
      "yes_bid_cents": 0.0,
      "yes_ask_cents": 0.0,
      "volume": 0.0
    },
    {
      "ticker": "KXAVAX-26FEB1510-B12.75",
      "title": "Avalanche price range  on Feb 15, 2026?",
      "yes_bid_cents": 0.0,
      "yes_ask_cents": 0.0,
      "volume": 0.0
    },
    {
      "ticker": "KXDOT-26FEB1510-B-1.95",
      "title": "Polkdadot price  on Feb 15, 2026?",
      "yes_bid_cents": 0.0,
      "yes_ask_cents": 0.0,
      "volume": 0.0
    },
    {
      "ticker": "KXBCHD-26FEB1510-T714.999",
      "title": "Bitcoin Cash price  on Feb 15, 2026?",
      "yes_bid_cents": 0.0,
      "yes_ask_cents": 0.0,
      "volume": 0.0
    },
    {
      "ticker": "KXAVAXD-26FEB1510-T17.9999",
      "title": "Avalanche price  on Feb 15, 2026?",
      "yes_bid_cents": 0.0,
      "yes_ask_cents": 0.0,
      "volume": 0.0
    },
    {
      "ticker": "KXAVAXD-26FEB1510-T23.4999",
      "title": "Avalanche price  on Feb 15, 2026?",
      "yes_bid_cents": 0.0,
      "yes_ask_cents": 0.0,
      "volume": 0.0
    },
    {
      "ticker": "KXDOT-26FEB1510-B3.55",
      "title": "Polkdadot price  on Feb 15, 2026?",
      "yes_bid_cents": 0.0,
      "yes_ask_cents": 0.0,
      "volume": 0.0
    },
    {
      "ticker": "KXAVAX-26FEB1510-B19.25",
      "title": "Avalanche price range  on Feb 15, 2026?",
      "yes_bid_cents": 0.0,
      "yes_ask_cents": 0.0,
      "volume": 0.0
    },
    {
      "ticker": "KXAVAXD-26FEB1510-T14.9999",
      "title": "Avalanche price  on Feb 15, 2026?",
      "yes_bid_cents": 0.0,
      "yes_ask_cents": 0.0,
      "volume": 0.0
    },
    {
      "ticker": "KXLTCD-26FEB1510-T60.9999",
      "title": "Litecoin price  on Feb 15, 2026?",
      "yes_bid_cents": 0.0,
      "yes_ask_cents": 0.0,
      "volume": 0.0
    },
    {
      "ticker": "KXLTC-26FEB1510-B22.5",
      "title": "Litecoin price range  on Feb 15, 2026?",
      "yes_bid_cents": 0.0,
      "yes_ask_cents": 0.0,
      "volume": 0.0
    },
    {
      "ticker": "KXXRPD-26FEB1510-T1.13999",
      "title": "Ripple price  on Feb 15, 2026?",
      "yes_bid_cents": 0.0,
      "yes_ask_cents": 0.0,
      "volume": 0.0
    },
    {
      "ticker": "KXXRPD-26FEB1510-T1.49999",
      "title": "Ripple price  on Feb 15, 2026?",
      "yes_bid_cents": 0.0,
      "yes_ask_cents": 0.0,
      "volume": 0.0
    },
    {
      "ticker": "KXDOT-26FEB1510-B0.05",
      "title": "Polkdadot price  on Feb 15, 2026?",
      "yes_bid_cents": 0.0,
      "yes_ask_cents": 0.0,
      "volume": 0.0
    },
    {
      "ticker": "KXBCHD-26FEB1510-T619.999",
      "title": "Bitcoin Cash price  on Feb 15, 2026?",
      "yes_bid_cents": 0.0,
      "yes_ask_cents": 0.0,
      "volume": 0.0
    },
    {
      "ticker": "KXLTCD-26FEB1510-T89.9999",
      "title": "Litecoin price  on Feb 15, 2026?",
      "yes_bid_cents": 0.0,
      "yes_ask_cents": 0.0,
      "volume": 0.0
    },
    {
      "ticker": "KXLINKD-26FEB1510-T1.79999",
      "title": "Chainlink price  on Feb 15, 2026?",
      "yes_bid_cents": 0.0,
      "yes_ask_cents": 0.0,
      "volume": 0.0
    },
    {
      "ticker": "KXHIGHMIA-26FEB15-B74.5",
      "title": "Will the **high temp in Miami** be 74-75° on Feb 15, 2026?",
      "yes_bid_cents": 0.0,
      "yes_ask_cents": 0.0,
      "volume": 0.0
    },
    {
      "ticker": "KXXLMD-26FEB1510-T-0.1300001",
      "title": "XLM price  on Feb 15, 2026?",
      "yes_bid_cents": 0.0,
      "yes_ask_cents": 0.0,
      "volume": 0.0
    },
    {
      "ticker": "KXLINK-26FEB1510-B9.90",
      "title": "Chainlink price  on Feb 15, 2026?",
      "yes_bid_cents": 0.0,
      "yes_ask_cents": 0.0,
      "volume": 0.0
    },
    {
      "ticker": "KXXRP-26FEB1510-T2.13999",
      "title": "Ripple price  on Feb 15, 2026?",
      "yes_bid_cents": 0.0,
      "yes_ask_cents": 0.0,
      "volume": 0.0
    },
    {
      "ticker": "KXBCHD-26FEB1510-T424.999",
      "title": "Bitcoin Cash price  on Feb 15, 2026?",
      "yes_bid_cents": 0.0,
      "yes_ask_cents": 0.0,
      "volume": 0.0
    },
    {
      "ticker": "KXLINK-26FEB1510-B12.30",
      "title": "Chainlink price  on Feb 15, 2026?",
      "yes_bid_cents": 0.0,
      "yes_ask_cents": 0.0,
      "volume": 0.0
    },
    {
      "ticker": "KXXLM-26FEB1510-B0.0050000",
      "title": "XLM price  on Feb 15, 2026?",
      "yes_bid_cents": 0.0,
      "yes_ask_cents": 0.0,
      "volume": 0.0
    },
    {
      "ticker": "KXXRPD-26FEB1510-T1.03999",
      "title": "Ripple price  on Feb 15, 2026?",
      "yes_bid_cents": 0.0,
      "yes_ask_cents": 0.0,
      "volume": 0.0
    },
    {
      "ticker": "KXLINKD-26FEB1510-T1.59999",
      "title": "Chainlink price  on Feb 15, 2026?",
      "yes_bid_cents": 0.0,
      "yes_ask_cents": 0.0,
      "volume": 0.0
    },
    {
      "ticker": "KXDOT-26FEB1510-B-2.25",
      "title": "Polkdadot price  on Feb 15, 2026?",
      "yes_bid_cents": 0.0,
      "yes_ask_cents": 0.0,
      "volume": 0.0
    },
    {
      "ticker": "KXHIGHHOU-26FEB15-T69",
      "title": "Will the **high temp in Houston** be <69° on Feb 15, 2026?",
      "yes_bid_cents": 0.0,
      "yes_ask_cents": 0.0,
      "volume": 0.0
    },
    {
      "ticker": "KXLTC-26FEB1510-B75.5",
      "title": "Litecoin price range  on Feb 15, 2026?",
      "yes_bid_cents": 0.0,
      "yes_ask_cents": 0.0,
      "volume": 0.0
    },
    {
      "ticker": "KXLTC-26FEB1510-B71.5",
      "title": "Litecoin price range  on Feb 15, 2026?",
      "yes_bid_cents": 0.0,
      "yes_ask_cents": 0.0,
      "volume": 0.0
    },
    {
      "ticker": "KXXRPD-26FEB1510-T2.11999",
      "title": "Ripple price  on Feb 15, 2026?",
      "yes_bid_cents": 0.0,
      "yes_ask_cents": 0.0,
      "volume": 0.0
    },
    {
      "ticker": "KXDOT-26FEB1510-B3.35",
      "title": "Polkdadot price  on Feb 15, 2026?",
      "yes_bid_cents": 0.0,
      "yes_ask_cents": 0.0,
      "volume": 0.0
    },
    {
      "ticker": "KXAVAXD-26FEB1510-T18.9999",
      "title": "Avalanche price  on Feb 15, 2026?",
      "yes_bid_cents": 0.0,
      "yes_ask_cents": 0.0,
      "volume": 0.0
    },
    {
      "ticker": "KXXRP-26FEB1510-B1.270",
      "title": "Ripple price  on Feb 15, 2026?",
      "yes_bid_cents": 0.0,
      "yes_ask_cents": 0.0,
      "volume": 0.0
    },
    {
      "ticker": "KXDOTD-26FEB1510-T4.39999",
      "title": "Polkdadot price  on Feb 15, 2026?",
      "yes_bid_cents": 0.0,
      "yes_ask_cents": 0.0,
      "volume": 0.0
    },
    {
      "ticker": "KXDOT-26FEB1510-B-0.25",
      "title": "Polkdadot price  on Feb 15, 2026?",
      "yes_bid_cents": 0.0,
      "yes_ask_cents": 0.0,
      "volume": 0.0
    },
    {
      "ticker": "KXBCHD-26FEB1510-T539.999",
      "title": "Bitcoin Cash price  on Feb 15, 2026?",
      "yes_bid_cents": 0.0,
      "yes_ask_cents": 0.0,
      "volume": 0.0
    },
    {
      "ticker": "KXLINKD-26FEB1510-T11.79999",
      "title": "Chainlink price  on Feb 15, 2026?",
      "yes_bid_cents": 0.0,
      "yes_ask_cents": 0.0,
      "volume": 0.0
    },
    {
      "ticker": "KXDOT-26FEB1510-B2.05",
      "title": "Polkdadot price  on Feb 15, 2026?",
      "yes_bid_cents": 0.0,
      "yes_ask_cents": 0.0,
      "volume": 0.0
    },
    {
      "ticker": "KXLINK-26FEB1510-T0.80000",
      "title": "Chainlink price  on Feb 15, 2026?",
      "yes_bid_cents": 0.0,
      "yes_ask_cents": 0.0,
      "volume": 0.0
    },
    {
      "ticker": "KXAVAX-26FEB1510-B-7.75",
      "title": "Avalanche price range  on Feb 15, 2026?",
      "yes_bid_cents": 0.0,
      "yes_ask_cents": 0.0,
      "volume": 0.0
    },
    {
      "ticker": "KXBCHD-26FEB1510-T419.999",
      "title": "Bitcoin Cash price  on Feb 15, 2026?",
      "yes_bid_cents": 0.0,
      "yes_ask_cents": 0.0,
      "volume": 0.0
    },
    {
      "ticker": "KXLTCD-26FEB1510-T90.9999",
      "title": "Litecoin price  on Feb 15, 2026?",
      "yes_bid_cents": 0.0,
      "yes_ask_cents": 0.0,
      "volume": 0.0
    },
    {
      "ticker": "KXDOTD-26FEB1510-T0.49999",
      "title": "Polkdadot price  on Feb 15, 2026?",
      "yes_bid_cents": 0.0,
      "yes_ask_cents": 0.0,
      "volume": 0.0
    },
    {
      "ticker": "KXLINK-26FEB1510-B10.30",
      "title": "Chainlink price  on Feb 15, 2026?",
      "yes_bid_cents": 0.0,
      "yes_ask_cents": 0.0,
      "volume": 0.0
    },
    {
      "ticker": "KXLTC-26FEB1510-B83.5",
      "title": "Litecoin price range  on Feb 15, 2026?",
      "yes_bid_cents": 0.0,
      "yes_ask_cents": 0.0,
      "volume": 0.0
    },
    {
      "ticker": "KXAVAX-26FEB1510-B-5.25",
      "title": "Avalanche price range  on Feb 15, 2026?",
      "yes_bid_cents": 0.0,
      "yes_ask_cents": 0.0,
      "volume": 0.0
    },
    {
      "ticker": "KXDOTD-26FEB1510-T4.49999",
      "title": "Polkdadot price  on Feb 15, 2026?",
      "yes_bid_cents": 0.0,
      "yes_ask_cents": 0.0,
      "volume": 0.0
    },
    {
      "ticker": "KXLINK-26FEB1510-B9.50",
      "title": "Chainlink price  on Feb 15, 2026?",
      "yes_bid_cents": 0.0,
      "yes_ask_cents": 0.0,
      "volume": 0.0
    },
    {
      "ticker": "KXAVAX-26FEB1510-B-6.25",
      "title": "Avalanche price range  on Feb 15, 2026?",
      "yes_bid_cents": 0.0,
      "yes_ask_cents": 0.0,
      "volume": 0.0
    },
    {
      "ticker": "KXAVAXD-26FEB1510-T24.4999",
      "title": "Avalanche price  on Feb 15, 2026?",
      "yes_bid_cents": 0.0,
      "yes_ask_cents": 0.0,
      "volume": 0.0
    },
    {
      "ticker": "KXXLM-26FEB1510-B0.0750000",
      "title": "XLM price  on Feb 15, 2026?",
      "yes_bid_cents": 0.0,
      "yes_ask_cents": 0.0,
      "volume": 0.0
    },
    {
      "ticker": "KXXRP-26FEB1510-B1.010",
      "title": "Ripple price  on Feb 15, 2026?",
      "yes_bid_cents": 0.0,
      "yes_ask_cents": 0.0,
      "volume": 0.0
    },
    {
      "ticker": "KXLINKD-26FEB1510-T3.79999",
      "title": "Chainlink price  on Feb 15, 2026?",
      "yes_bid_cents": 0.0,
      "yes_ask_cents": 0.0,
      "volume": 0.0
    },
    {
      "ticker": "KXAVAXD-26FEB1510-T7.9999",
      "title": "Avalanche price  on Feb 15, 2026?",
      "yes_bid_cents": 0.0,
      "yes_ask_cents": 0.0,
      "volume": 0.0
    },
    {
      "ticker": "KXHIGHMIA-26FEB15-B76.5",
      "title": "Will the **high temp in Miami** be 76-77° on Feb 15, 2026?",
      "yes_bid_cents": 0.0,
      "yes_ask_cents": 0.0,
      "volume": 0.0
    },
    {
      "ticker": "KXXLM-26FEB1510-B-0.1050000",
      "title": "XLM price  on Feb 15, 2026?",
      "yes_bid_cents": 0.0,
      "yes_ask_cents": 0.0,
      "volume": 0.0
    },
    {
      "ticker": "KXXRP-26FEB1510-B1.050",
      "title": "Ripple price  on Feb 15, 2026?",
      "yes_bid_cents": 0.0,
      "yes_ask_cents": 0.0,
      "volume": 0.0
    },
    {
      "ticker": "KXLTCD-26FEB1510-T75.9999",
      "title": "Litecoin price  on Feb 15, 2026?",
      "yes_bid_cents": 0.0,
      "yes_ask_cents": 0.0,
      "volume": 0.0
    },
    {
      "ticker": "KXXLM-26FEB1510-B-0.1250001",
      "title": "XLM price  on Feb 15, 2026?",
      "yes_bid_cents": 0.0,
      "yes_ask_cents": 0.0,
      "volume": 0.0
    },
    {
      "ticker": "KXLTCD-26FEB1510-T18.9999",
      "title": "Litecoin price  on Feb 15, 2026?",
      "yes_bid_cents": 0.0,
      "yes_ask_cents": 0.0,
      "volume": 0.0
    },
    {
      "ticker": "KXLTCD-26FEB1510-T64.9999",
      "title": "Litecoin price  on Feb 15, 2026?",
      "yes_bid_cents": 0.0,
      "yes_ask_cents": 0.0,
      "volume": 0.0
    },
    {
      "ticker": "KXLINK-26FEB1510-B12.50",
      "title": "Chainlink price  on Feb 15, 2026?",
      "yes_bid_cents": 0.0,
      "yes_ask_cents": 0.0,
      "volume": 0.0
    },
    {
      "ticker": "KXXRPD-26FEB1510-T1.63999",
      "title": "Ripple price  on Feb 15, 2026?",
      "yes_bid_cents": 0.0,
      "yes_ask_cents": 0.0,
      "volume": 0.0
    },
    {
      "ticker": "KXLTC-26FEB1510-B58.5",
      "title": "Litecoin price range  on Feb 15, 2026?",
      "yes_bid_cents": 0.0,
      "yes_ask_cents": 0.0,
      "volume": 0.0
    },
    {
      "ticker": "KXAVAX-26FEB1510-B2.25",
      "title": "Avalanche price range  on Feb 15, 2026?",
      "yes_bid_cents": 0.0,
      "yes_ask_cents": 0.0,
      "volume": 0.0
    },
    {
      "ticker": "KXAVAX-26FEB1510-B13.75",
      "title": "Avalanche price range  on Feb 15, 2026?",
      "yes_bid_cents": 0.0,
      "yes_ask_cents": 0.0,
      "volume": 0.0
    },
    {
      "ticker": "KXXLMD-26FEB1510-T0.2699999",
      "title": "XLM price  on Feb 15, 2026?",
      "yes_bid_cents": 0.0,
      "yes_ask_cents": 0.0,
      "volume": 0.0
    },
    {
      "ticker": "KXXLM-26FEB1510-B0.1950000",
      "title": "XLM price  on Feb 15, 2026?",
      "yes_bid_cents": 0.0,
      "yes_ask_cents": 0.0,
      "volume": 0.0
    },
    {
      "ticker": "KXAVAXD-26FEB1510-T20.4999",
      "title": "Avalanche price  on Feb 15, 2026?",
      "yes_bid_cents": 0.0,
      "yes_ask_cents": 0.0,
      "volume": 0.0
    }
  ],
  "valuations": [
    {
      "ticker": "KXXRPD-26FEB1510-T2.09999",
      "fair_prob_yes": 0.01,
      "market_mid_prob_yes": 0.01,
      "market_volume": 0.0,
      "spread_cents": 0.0,
      "confidence": 0.45,
      "rationale": "heuristic valuation fallback",
      "stale_after": "2026-02-15T14:55:27.281293Z"
    },
    {
      "ticker": "KXXLMD-26FEB1510-T-0.0400001",
      "fair_prob_yes": 0.01,
      "market_mid_prob_yes": 0.01,
      "market_volume": 0.0,
      "spread_cents": 0.0,
      "confidence": 0.45,
      "rationale": "heuristic valuation fallback",
      "stale_after": "2026-02-15T14:55:27.282278Z"
    },
    {
      "ticker": "KXLTCD-26FEB1510-T82.9999",
      "fair_prob_yes": 0.01,
      "market_mid_prob_yes": 0.01,
      "market_volume": 0.0,
      "spread_cents": 0.0,
      "confidence": 0.62,
      "rationale": "heuristic valuation fallback",
      "stale_after": "2026-02-15T14:55:27.280774Z"
    },
    {
      "ticker": "KXDOTD-26FEB1510-T-1.60001",
      "fair_prob_yes": 0.01,
      "market_mid_prob_yes": 0.01,
      "market_volume": 0.0,
      "spread_cents": 0.0,
      "confidence": 0.45,
      "rationale": "heuristic valuation fallback",
      "stale_after": "2026-02-15T14:55:27.280790Z"
    },
    {
      "ticker": "KXLINKD-26FEB1510-T5.19999",
      "fair_prob_yes": 0.01,
      "market_mid_prob_yes": 0.01,
      "market_volume": 0.0,
      "spread_cents": 0.0,
      "confidence": 0.45,
      "rationale": "heuristic valuation fallback",
      "stale_after": "2026-02-15T14:55:27.281642Z"
    },
    {
      "ticker": "KXDOT-26FEB1510-B-0.15",
      "fair_prob_yes": 0.01,
      "market_mid_prob_yes": 0.01,
      "market_volume": 0.0,
      "spread_cents": 0.0,
      "confidence": 0.45,
      "rationale": "heuristic valuation fallback",
      "stale_after": "2026-02-15T14:55:27.281282Z"
    },
    {
      "ticker": "KXLTCD-26FEB1510-T78.9999",
      "fair_prob_yes": 0.01,
      "market_mid_prob_yes": 0.01,
      "market_volume": 0.0,
      "spread_cents": 0.0,
      "confidence": 0.45,
      "rationale": "heuristic valuation fallback",
      "stale_after": "2026-02-15T14:55:27.281984Z"
    },
    {
      "ticker": "KXXLMD-26FEB1510-T-0.1200001",
      "fair_prob_yes": 0.01,
      "market_mid_prob_yes": 0.01,
      "market_volume": 0.0,
      "spread_cents": 0.0,
      "confidence": 0.62,
      "rationale": "heuristic valuation fallback",
      "stale_after": "2026-02-15T14:55:27.280754Z"
    },
    {
      "ticker": "KXLTC-26FEB1510-B39.5",
      "fair_prob_yes": 0.01,
      "market_mid_prob_yes": 0.01,
      "market_volume": 0.0,
      "spread_cents": 0.0,
      "confidence": 0.45,
      "rationale": "heuristic valuation fallback",
      "stale_after": "2026-02-15T14:55:27.281989Z"
    },
    {
      "ticker": "KXAVAX-26FEB1510-B4.25",
      "fair_prob_yes": 0.01,
      "market_mid_prob_yes": 0.01,
      "market_volume": 0.0,
      "spread_cents": 0.0,
      "confidence": 0.45,
      "rationale": "heuristic valuation fallback",
      "stale_after": "2026-02-15T14:55:27.282274Z"
    },
    {
      "ticker": "KXDOTD-26FEB1510-T0.79999",
      "fair_prob_yes": 0.01,
      "market_mid_prob_yes": 0.01,
      "market_volume": 0.0,
      "spread_cents": 0.0,
      "confidence": 0.62,
      "rationale": "heuristic valuation fallback",
      "stale_after": "2026-02-15T15:05:26.275971Z"
    },
    {
      "ticker": "KXXLMD-26FEB1510-T-0.2600001",
      "fair_prob_yes": 0.01,
      "market_mid_prob_yes": 0.01,
      "market_volume": 0.0,
      "spread_cents": 0.0,
      "confidence": 0.62,
      "rationale": "heuristic valuation fallback",
      "stale_after": "2026-02-15T15:05:26.275973Z"
    },
    {
      "ticker": "KXDOTD-26FEB1510-T1.79999",
      "fair_prob_yes": 0.01,
      "market_mid_prob_yes": 0.01,
      "market_volume": 0.0,
      "spread_cents": 0.0,
      "confidence": 0.62,
      "rationale": "heuristic valuation fallback",
      "stale_after": "2026-02-15T15:05:26.275973Z"
    },
    {
      "ticker": "KXLTC-26FEB1510-B67.5",
      "fair_prob_yes": 0.01,
      "market_mid_prob_yes": 0.01,
      "market_volume": 0.0,
      "spread_cents": 0.0,
      "confidence": 0.62,
      "rationale": "heuristic valuation fallback",
      "stale_after": "2026-02-15T15:05:26.275974Z"
    },
    {
      "ticker": "KXXLMD-26FEB1510-T-0.1600001",
      "fair_prob_yes": 0.01,
      "market_mid_prob_yes": 0.01,
      "market_volume": 0.0,
      "spread_cents": 0.0,
      "confidence": 0.62,
      "rationale": "heuristic valuation fallback",
      "stale_after": "2026-02-15T15:05:26.275975Z"
    },
    {
      "ticker": "KXXRPD-26FEB1510-T1.17999",
      "fair_prob_yes": 0.01,
      "market_mid_prob_yes": 0.01,
      "market_volume": 0.0,
      "spread_cents": 0.0,
      "confidence": 0.62,
      "rationale": "heuristic valuation fallback",
      "stale_after": "2026-02-15T15:05:26.275976Z"
    },
    {
      "ticker": "KXDOTD-26FEB1510-T0.19999",
      "fair_prob_yes": 0.01,
      "market_mid_prob_yes": 0.01,
      "market_volume": 0.0,
      "spread_cents": 0.0,
      "confidence": 0.62,
      "rationale": "heuristic valuation fallback",
      "stale_after": "2026-02-15T15:05:26.275976Z"
    },
    {
      "ticker": "KXDOTD-26FEB1510-T-0.50001",
      "fair_prob_yes": 0.01,
      "market_mid_prob_yes": 0.01,
      "market_volume": 0.0,
      "spread_cents": 0.0,
      "confidence": 0.62,
      "rationale": "heuristic valuation fallback",
      "stale_after": "2026-02-15T15:05:26.275977Z"
    },
    {
      "ticker": "KXLINKD-26FEB1510-T5.59999",
      "fair_prob_yes": 0.01,
      "market_mid_prob_yes": 0.01,
      "market_volume": 0.0,
      "spread_cents": 0.0,
      "confidence": 0.62,
      "rationale": "heuristic valuation fallback",
      "stale_after": "2026-02-15T15:05:26.275978Z"
    },
    {
      "ticker": "KXDOT-26FEB1510-B-1.65",
      "fair_prob_yes": 0.01,
      "market_mid_prob_yes": 0.01,
      "market_volume": 0.0,
      "spread_cents": 0.0,
      "confidence": 0.62,
      "rationale": "heuristic valuation fallback",
      "stale_after": "2026-02-15T15:05:26.275978Z"
    },
    {
      "ticker": "KXXLMD-26FEB1510-T-0.0100001",
      "fair_prob_yes": 0.01,
      "market_mid_prob_yes": 0.01,
      "market_volume": 0.0,
      "spread_cents": 0.0,
      "confidence": 0.62,
      "rationale": "heuristic valuation fallback",
      "stale_after": "2026-02-15T15:05:26.275979Z"
    },
    {
      "ticker": "KXXLMD-26FEB1510-T0.0699999",
      "fair_prob_yes": 0.01,
      "market_mid_prob_yes": 0.01,
      "market_volume": 0.0,
      "spread_cents": 0.0,
      "confidence": 0.62,
      "rationale": "heuristic valuation fallback",
      "stale_after": "2026-02-15T15:05:26.275980Z"
    },
    {
      "ticker": "KXXRPD-26FEB1510-T1.47999",
      "fair_prob_yes": 0.01,
      "market_mid_prob_yes": 0.01,
      "market_volume": 0.0,
      "spread_cents": 0.0,
      "confidence": 0.62,
      "rationale": "heuristic valuation fallback",
      "stale_after": "2026-02-15T15:05:26.275980Z"
    },
    {
      "ticker": "KXLTCD-26FEB1510-T68.9999",
      "fair_prob_yes": 0.01,
      "market_mid_prob_yes": 0.01,
      "market_volume": 0.0,
      "spread_cents": 0.0,
      "confidence": 0.62,
      "rationale": "heuristic valuation fallback",
      "stale_after": "2026-02-15T15:05:26.275981Z"
    },
    {
      "ticker": "KXAVAXD-26FEB1510-T8.9999",
      "fair_prob_yes": 0.01,
      "market_mid_prob_yes": 0.01,
      "market_volume": 0.0,
      "spread_cents": 0.0,
      "confidence": 0.62,
      "rationale": "heuristic valuation fallback",
      "stale_after": "2026-02-15T15:05:26.275982Z"
    },
    {
      "ticker": "KXBCHD-26FEB1510-T459.999",
      "fair_prob_yes": 0.01,
      "market_mid_prob_yes": 0.01,
      "market_volume": 0.0,
      "spread_cents": 0.0,
      "confidence": 0.62,
      "rationale": "heuristic valuation fallback",
      "stale_after": "2026-02-15T15:05:26.275982Z"
    },
    {
      "ticker": "KXXLMD-26FEB1510-T0.3899999",
      "fair_prob_yes": 0.01,
      "market_mid_prob_yes": 0.01,
      "market_volume": 0.0,
      "spread_cents": 0.0,
      "confidence": 0.62,
      "rationale": "heuristic valuation fallback",
      "stale_after": "2026-02-15T15:05:26.275983Z"
    },
    {
      "ticker": "KXXRP-26FEB1510-B0.870",
      "fair_prob_yes": 0.01,
      "market_mid_prob_yes": 0.01,
      "market_volume": 0.0,
      "spread_cents": 0.0,
      "confidence": 0.62,
      "rationale": "heuristic valuation fallback",
      "stale_after": "2026-02-15T15:05:26.275984Z"
    },
    {
      "ticker": "KXXLM-26FEB1510-B0.4450000",
      "fair_prob_yes": 0.01,
      "market_mid_prob_yes": 0.01,
      "market_volume": 0.0,
      "spread_cents": 0.0,
      "confidence": 0.45,
      "rationale": "heuristic valuation fallback",
      "stale_after": "2026-02-15T15:05:26.275985Z"
    },
    {
      "ticker": "KXLTCD-26FEB1510-T44.9999",
      "fair_prob_yes": 0.01,
      "market_mid_prob_yes": 0.01,
      "market_volume": 0.0,
      "spread_cents": 0.0,
      "confidence": 0.45,
      "rationale": "heuristic valuation fallback",
      "stale_after": "2026-02-15T15:05:26.275985Z"
    },
    {
      "ticker": "KXLTCD-26FEB1510-T41.9999",
      "fair_prob_yes": 0.01,
      "market_mid_prob_yes": 0.01,
      "market_volume": 0.0,
      "spread_cents": 0.0,
      "confidence": 0.45,
      "rationale": "heuristic valuation fallback",
      "stale_after": "2026-02-15T15:05:26.275986Z"
    },
    {
      "ticker": "KXAVAX-26FEB1510-B12.75",
      "fair_prob_yes": 0.01,
      "market_mid_prob_yes": 0.01,
      "market_volume": 0.0,
      "spread_cents": 0.0,
      "confidence": 0.45,
      "rationale": "heuristic valuation fallback",
      "stale_after": "2026-02-15T15:05:26.275986Z"
    },
    {
      "ticker": "KXLTC-26FEB1510-B22.5",
      "fair_prob_yes": 0.01,
      "market_mid_prob_yes": 0.01,
      "market_volume": 0.0,
      "spread_cents": 0.0,
      "confidence": 0.45,
      "rationale": "heuristic valuation fallback",
      "stale_after": "2026-02-15T14:55:27.281633Z"
    },
    {
      "ticker": "KXBCHD-26FEB1510-T619.999",
      "fair_prob_yes": 0.01,
      "market_mid_prob_yes": 0.01,
      "market_volume": 0.0,
      "spread_cents": 0.0,
      "confidence": 0.45,
      "rationale": "heuristic valuation fallback",
      "stale_after": "2026-02-15T14:55:27.281982Z"
    },
    {
      "ticker": "KXLTCD-26FEB1510-T89.9999",
      "fair_prob_yes": 0.01,
      "market_mid_prob_yes": 0.01,
      "market_volume": 0.0,
      "spread_cents": 0.0,
      "confidence": 0.45,
      "rationale": "heuristic valuation fallback",
      "stale_after": "2026-02-15T14:55:27.281635Z"
    },
    {
      "ticker": "KXLTC-26FEB1510-B71.5",
      "fair_prob_yes": 0.01,
      "market_mid_prob_yes": 0.01,
      "market_volume": 0.0,
      "spread_cents": 0.0,
      "confidence": 0.45,
      "rationale": "heuristic valuation fallback",
      "stale_after": "2026-02-15T14:55:27.280788Z"
    },
    {
      "ticker": "KXDOT-26FEB1510-B-1.95",
      "fair_prob_yes": 0.01,
      "market_mid_prob_yes": 0.01,
      "market_volume": 0.0,
      "spread_cents": 0.0,
      "confidence": 0.45,
      "rationale": "heuristic valuation fallback",
      "stale_after": "2026-02-15T15:05:26.276206Z"
    },
    {
      "ticker": "KXBCHD-26FEB1510-T714.999",
      "fair_prob_yes": 0.01,
      "market_mid_prob_yes": 0.01,
      "market_volume": 0.0,
      "spread_cents": 0.0,
      "confidence": 0.45,
      "rationale": "heuristic valuation fallback",
      "stale_after": "2026-02-15T15:05:26.276207Z"
    },
    {
      "ticker": "KXAVAXD-26FEB1510-T17.9999",
      "fair_prob_yes": 0.01,
      "market_mid_prob_yes": 0.01,
      "market_volume": 0.0,
      "spread_cents": 0.0,
      "confidence": 0.45,
      "rationale": "heuristic valuation fallback",
      "stale_after": "2026-02-15T15:05:26.276208Z"
    },
    {
      "ticker": "KXAVAXD-26FEB1510-T23.4999",
      "fair_prob_yes": 0.01,
      "market_mid_prob_yes": 0.01,
      "market_volume": 0.0,
      "spread_cents": 0.0,
      "confidence": 0.45,
      "rationale": "heuristic valuation fallback",
      "stale_after": "2026-02-15T15:05:26.276209Z"
    },
    {
      "ticker": "KXDOT-26FEB1510-B3.55",
      "fair_prob_yes": 0.01,
      "market_mid_prob_yes": 0.01,
      "market_volume": 0.0,
      "spread_cents": 0.0,
      "confidence": 0.45,
      "rationale": "heuristic valuation fallback",
      "stale_after": "2026-02-15T15:05:26.276209Z"
    },
    {
      "ticker": "KXAVAX-26FEB1510-B19.25",
      "fair_prob_yes": 0.01,
      "market_mid_prob_yes": 0.01,
      "market_volume": 0.0,
      "spread_cents": 0.0,
      "confidence": 0.45,
      "rationale": "heuristic valuation fallback",
      "stale_after": "2026-02-15T15:05:26.276210Z"
    },
    {
      "ticker": "KXAVAXD-26FEB1510-T14.9999",
      "fair_prob_yes": 0.01,
      "market_mid_prob_yes": 0.01,
      "market_volume": 0.0,
      "spread_cents": 0.0,
      "confidence": 0.45,
      "rationale": "heuristic valuation fallback",
      "stale_after": "2026-02-15T15:05:26.276210Z"
    },
    {
      "ticker": "KXLTCD-26FEB1510-T60.9999",
      "fair_prob_yes": 0.01,
      "market_mid_prob_yes": 0.01,
      "market_volume": 0.0,
      "spread_cents": 0.0,
      "confidence": 0.45,
      "rationale": "heuristic valuation fallback",
      "stale_after": "2026-02-15T15:05:26.276211Z"
    },
    {
      "ticker": "KXXRPD-26FEB1510-T1.13999",
      "fair_prob_yes": 0.01,
      "market_mid_prob_yes": 0.01,
      "market_volume": 0.0,
      "spread_cents": 0.0,
      "confidence": 0.45,
      "rationale": "heuristic valuation fallback",
      "stale_after": "2026-02-15T15:05:26.276212Z"
    },
    {
      "ticker": "KXXRPD-26FEB1510-T1.49999",
      "fair_prob_yes": 0.01,
      "market_mid_prob_yes": 0.01,
      "market_volume": 0.0,
      "spread_cents": 0.0,
      "confidence": 0.45,
      "rationale": "heuristic valuation fallback",
      "stale_after": "2026-02-15T15:05:26.276212Z"
    },
    {
      "ticker": "KXDOT-26FEB1510-B0.05",
      "fair_prob_yes": 0.01,
      "market_mid_prob_yes": 0.01,
      "market_volume": 0.0,
      "spread_cents": 0.0,
      "confidence": 0.45,
      "rationale": "heuristic valuation fallback",
      "stale_after": "2026-02-15T15:05:26.276213Z"
    },
    {
      "ticker": "KXLINKD-26FEB1510-T1.79999",
      "fair_prob_yes": 0.01,
      "market_mid_prob_yes": 0.01,
      "market_volume": 0.0,
      "spread_cents": 0.0,
      "confidence": 0.45,
      "rationale": "heuristic valuation fallback",
      "stale_after": "2026-02-15T15:05:26.276214Z"
    },
    {
      "ticker": "KXHIGHMIA-26FEB15-B74.5",
      "fair_prob_yes": 0.01,
      "market_mid_prob_yes": 0.01,
      "market_volume": 0.0,
      "spread_cents": 0.0,
      "confidence": 0.45,
      "rationale": "heuristic valuation fallback",
      "stale_after": "2026-02-15T15:05:26.276214Z"
    },
    {
      "ticker": "KXXLMD-26FEB1510-T-0.1300001",
      "fair_prob_yes": 0.01,
      "market_mid_prob_yes": 0.01,
      "market_volume": 0.0,
      "spread_cents": 0.0,
      "confidence": 0.45,
      "rationale": "heuristic valuation fallback",
      "stale_after": "2026-02-15T15:05:26.276215Z"
    },
    {
      "ticker": "KXLINK-26FEB1510-B9.90",
      "fair_prob_yes": 0.01,
      "market_mid_prob_yes": 0.01,
      "market_volume": 0.0,
      "spread_cents": 0.0,
      "confidence": 0.45,
      "rationale": "heuristic valuation fallback",
      "stale_after": "2026-02-15T15:05:26.276216Z"
    },
    {
      "ticker": "KXXRP-26FEB1510-T2.13999",
      "fair_prob_yes": 0.01,
      "market_mid_prob_yes": 0.01,
      "market_volume": 0.0,
      "spread_cents": 0.0,
      "confidence": 0.45,
      "rationale": "heuristic valuation fallback",
      "stale_after": "2026-02-15T15:05:26.276216Z"
    },
    {
      "ticker": "KXBCHD-26FEB1510-T424.999",
      "fair_prob_yes": 0.01,
      "market_mid_prob_yes": 0.01,
      "market_volume": 0.0,
      "spread_cents": 0.0,
      "confidence": 0.45,
      "rationale": "heuristic valuation fallback",
      "stale_after": "2026-02-15T15:05:26.276217Z"
    },
    {
      "ticker": "KXLINK-26FEB1510-B12.30",
      "fair_prob_yes": 0.01,
      "market_mid_prob_yes": 0.01,
      "market_volume": 0.0,
      "spread_cents": 0.0,
      "confidence": 0.45,
      "rationale": "heuristic valuation fallback",
      "stale_after": "2026-02-15T15:05:26.276217Z"
    },
    {
      "ticker": "KXXLM-26FEB1510-B0.0050000",
      "fair_prob_yes": 0.01,
      "market_mid_prob_yes": 0.01,
      "market_volume": 0.0,
      "spread_cents": 0.0,
      "confidence": 0.45,
      "rationale": "heuristic valuation fallback",
      "stale_after": "2026-02-15T15:05:26.276218Z"
    },
    {
      "ticker": "KXXRPD-26FEB1510-T1.03999",
      "fair_prob_yes": 0.01,
      "market_mid_prob_yes": 0.01,
      "market_volume": 0.0,
      "spread_cents": 0.0,
      "confidence": 0.45,
      "rationale": "heuristic valuation fallback",
      "stale_after": "2026-02-15T15:05:26.276219Z"
    },
    {
      "ticker": "KXLINKD-26FEB1510-T1.59999",
      "fair_prob_yes": 0.01,
      "market_mid_prob_yes": 0.01,
      "market_volume": 0.0,
      "spread_cents": 0.0,
      "confidence": 0.45,
      "rationale": "heuristic valuation fallback",
      "stale_after": "2026-02-15T15:05:26.276219Z"
    },
    {
      "ticker": "KXDOT-26FEB1510-B-2.25",
      "fair_prob_yes": 0.01,
      "market_mid_prob_yes": 0.01,
      "market_volume": 0.0,
      "spread_cents": 0.0,
      "confidence": 0.45,
      "rationale": "heuristic valuation fallback",
      "stale_after": "2026-02-15T15:05:26.276220Z"
    },
    {
      "ticker": "KXHIGHHOU-26FEB15-T69",
      "fair_prob_yes": 0.01,
      "market_mid_prob_yes": 0.01,
      "market_volume": 0.0,
      "spread_cents": 0.0,
      "confidence": 0.45,
      "rationale": "heuristic valuation fallback",
      "stale_after": "2026-02-15T15:05:26.276221Z"
    },
    {
      "ticker": "KXLTC-26FEB1510-B75.5",
      "fair_prob_yes": 0.01,
      "market_mid_prob_yes": 0.01,
      "market_volume": 0.0,
      "spread_cents": 0.0,
      "confidence": 0.45,
      "rationale": "heuristic valuation fallback",
      "stale_after": "2026-02-15T15:05:26.276221Z"
    },
    {
      "ticker": "KXXRPD-26FEB1510-T2.11999",
      "fair_prob_yes": 0.01,
      "market_mid_prob_yes": 0.01,
      "market_volume": 0.0,
      "spread_cents": 0.0,
      "confidence": 0.45,
      "rationale": "heuristic valuation fallback",
      "stale_after": "2026-02-15T15:05:26.276222Z"
    },
    {
      "ticker": "KXDOT-26FEB1510-B3.35",
      "fair_prob_yes": 0.01,
      "market_mid_prob_yes": 0.01,
      "market_volume": 0.0,
      "spread_cents": 0.0,
      "confidence": 0.45,
      "rationale": "heuristic valuation fallback",
      "stale_after": "2026-02-15T15:05:26.276223Z"
    },
    {
      "ticker": "KXAVAXD-26FEB1510-T18.9999",
      "fair_prob_yes": 0.01,
      "market_mid_prob_yes": 0.01,
      "market_volume": 0.0,
      "spread_cents": 0.0,
      "confidence": 0.45,
      "rationale": "heuristic valuation fallback",
      "stale_after": "2026-02-15T15:05:26.276223Z"
    },
    {
      "ticker": "KXXRP-26FEB1510-B1.270",
      "fair_prob_yes": 0.01,
      "market_mid_prob_yes": 0.01,
      "market_volume": 0.0,
      "spread_cents": 0.0,
      "confidence": 0.45,
      "rationale": "heuristic valuation fallback",
      "stale_after": "2026-02-15T15:05:26.276224Z"
    },
    {
      "ticker": "KXLTC-26FEB1510-B83.5",
      "fair_prob_yes": 0.01,
      "market_mid_prob_yes": 0.01,
      "market_volume": 0.0,
      "spread_cents": 0.0,
      "confidence": 0.62,
      "rationale": "heuristic valuation fallback",
      "stale_after": "2026-02-15T14:55:27.280764Z"
    },
    {
      "ticker": "KXAVAX-26FEB1510-B-6.25",
      "fair_prob_yes": 0.01,
      "market_mid_prob_yes": 0.01,
      "market_volume": 0.0,
      "spread_cents": 0.0,
      "confidence": 0.45,
      "rationale": "heuristic valuation fallback",
      "stale_after": "2026-02-15T14:55:27.282273Z"
    },
    {
      "ticker": "KXHIGHMIA-26FEB15-B76.5",
      "fair_prob_yes": 0.01,
      "market_mid_prob_yes": 0.01,
      "market_volume": 0.0,
      "spread_cents": 0.0,
      "confidence": 0.45,
      "rationale": "heuristic valuation fallback",
      "stale_after": "2026-02-15T14:55:27.281623Z"
    },
    {
      "ticker": "KXLTCD-26FEB1510-T18.9999",
      "fair_prob_yes": 0.01,
      "market_mid_prob_yes": 0.01,
      "market_volume": 0.0,
      "spread_cents": 0.0,
      "confidence": 0.45,
      "rationale": "heuristic valuation fallback",
      "stale_after": "2026-02-15T14:55:27.282277Z"
    },
    {
      "ticker": "KXDOTD-26FEB1510-T4.39999",
      "fair_prob_yes": 0.01,
      "market_mid_prob_yes": 0.01,
      "market_volume": 0.0,
      "spread_cents": 0.0,
      "confidence": 0.45,
      "rationale": "heuristic valuation fallback",
      "stale_after": "2026-02-15T15:05:26.276402Z"
    },
    {
      "ticker": "KXDOT-26FEB1510-B-0.25",
      "fair_prob_yes": 0.01,
      "market_mid_prob_yes": 0.01,
      "market_volume": 0.0,
      "spread_cents": 0.0,
      "confidence": 0.45,
      "rationale": "heuristic valuation fallback",
      "stale_after": "2026-02-15T15:05:26.276402Z"
    },
    {
      "ticker": "KXBCHD-26FEB1510-T539.999",
      "fair_prob_yes": 0.01,
      "market_mid_prob_yes": 0.01,
      "market_volume": 0.0,
      "spread_cents": 0.0,
      "confidence": 0.45,
      "rationale": "heuristic valuation fallback",
      "stale_after": "2026-02-15T15:05:26.276403Z"
    },
    {
      "ticker": "KXLINKD-26FEB1510-T11.79999",
      "fair_prob_yes": 0.01,
      "market_mid_prob_yes": 0.01,
      "market_volume": 0.0,
      "spread_cents": 0.0,
      "confidence": 0.45,
      "rationale": "heuristic valuation fallback",
      "stale_after": "2026-02-15T15:05:26.276404Z"
    },
    {
      "ticker": "KXDOT-26FEB1510-B2.05",
      "fair_prob_yes": 0.01,
      "market_mid_prob_yes": 0.01,
      "market_volume": 0.0,
      "spread_cents": 0.0,
      "confidence": 0.45,
      "rationale": "heuristic valuation fallback",
      "stale_after": "2026-02-15T15:05:26.276404Z"
    },
    {
      "ticker": "KXLINK-26FEB1510-T0.80000",
      "fair_prob_yes": 0.01,
      "market_mid_prob_yes": 0.01,
      "market_volume": 0.0,
      "spread_cents": 0.0,
      "confidence": 0.45,
      "rationale": "heuristic valuation fallback",
      "stale_after": "2026-02-15T15:05:26.276405Z"
    },
    {
      "ticker": "KXAVAX-26FEB1510-B-7.75",
      "fair_prob_yes": 0.01,
      "market_mid_prob_yes": 0.01,
      "market_volume": 0.0,
      "spread_cents": 0.0,
      "confidence": 0.45,
      "rationale": "heuristic valuation fallback",
      "stale_after": "2026-02-15T15:05:26.276406Z"
    },
    {
      "ticker": "KXBCHD-26FEB1510-T419.999",
      "fair_prob_yes": 0.01,
      "market_mid_prob_yes": 0.01,
      "market_volume": 0.0,
      "spread_cents": 0.0,
      "confidence": 0.45,
      "rationale": "heuristic valuation fallback",
      "stale_after": "2026-02-15T15:05:26.276406Z"
    },
    {
      "ticker": "KXLTCD-26FEB1510-T90.9999",
      "fair_prob_yes": 0.01,
      "market_mid_prob_yes": 0.01,
      "market_volume": 0.0,
      "spread_cents": 0.0,
      "confidence": 0.45,
      "rationale": "heuristic valuation fallback",
      "stale_after": "2026-02-15T15:05:26.276407Z"
    },
    {
      "ticker": "KXDOTD-26FEB1510-T0.49999",
      "fair_prob_yes": 0.01,
      "market_mid_prob_yes": 0.01,
      "market_volume": 0.0,
      "spread_cents": 0.0,
      "confidence": 0.45,
      "rationale": "heuristic valuation fallback",
      "stale_after": "2026-02-15T15:05:26.276408Z"
    },
    {
      "ticker": "KXLINK-26FEB1510-B10.30",
      "fair_prob_yes": 0.01,
      "market_mid_prob_yes": 0.01,
      "market_volume": 0.0,
      "spread_cents": 0.0,
      "confidence": 0.45,
      "rationale": "heuristic valuation fallback",
      "stale_after": "2026-02-15T15:05:26.276408Z"
    },
    {
      "ticker": "KXAVAX-26FEB1510-B-5.25",
      "fair_prob_yes": 0.01,
      "market_mid_prob_yes": 0.01,
      "market_volume": 0.0,
      "spread_cents": 0.0,
      "confidence": 0.45,
      "rationale": "heuristic valuation fallback",
      "stale_after": "2026-02-15T15:05:26.276409Z"
    },
    {
      "ticker": "KXDOTD-26FEB1510-T4.49999",
      "fair_prob_yes": 0.01,
      "market_mid_prob_yes": 0.01,
      "market_volume": 0.0,
      "spread_cents": 0.0,
      "confidence": 0.45,
      "rationale": "heuristic valuation fallback",
      "stale_after": "2026-02-15T15:05:26.276410Z"
    },
    {
      "ticker": "KXLINK-26FEB1510-B9.50",
      "fair_prob_yes": 0.01,
      "market_mid_prob_yes": 0.01,
      "market_volume": 0.0,
      "spread_cents": 0.0,
      "confidence": 0.45,
      "rationale": "heuristic valuation fallback",
      "stale_after": "2026-02-15T15:05:26.276410Z"
    },
    {
      "ticker": "KXAVAXD-26FEB1510-T24.4999",
      "fair_prob_yes": 0.01,
      "market_mid_prob_yes": 0.01,
      "market_volume": 0.0,
      "spread_cents": 0.0,
      "confidence": 0.45,
      "rationale": "heuristic valuation fallback",
      "stale_after": "2026-02-15T15:05:26.276411Z"
    },
    {
      "ticker": "KXXLM-26FEB1510-B0.0750000",
      "fair_prob_yes": 0.01,
      "market_mid_prob_yes": 0.01,
      "market_volume": 0.0,
      "spread_cents": 0.0,
      "confidence": 0.45,
      "rationale": "heuristic valuation fallback",
      "stale_after": "2026-02-15T15:05:26.276412Z"
    },
    {
      "ticker": "KXXRP-26FEB1510-B1.010",
      "fair_prob_yes": 0.01,
      "market_mid_prob_yes": 0.01,
      "market_volume": 0.0,
      "spread_cents": 0.0,
      "confidence": 0.45,
      "rationale": "heuristic valuation fallback",
      "stale_after": "2026-02-15T15:05:26.276412Z"
    },
    {
      "ticker": "KXLINKD-26FEB1510-T3.79999",
      "fair_prob_yes": 0.01,
      "market_mid_prob_yes": 0.01,
      "market_volume": 0.0,
      "spread_cents": 0.0,
      "confidence": 0.45,
      "rationale": "heuristic valuation fallback",
      "stale_after": "2026-02-15T15:05:26.276413Z"
    },
    {
      "ticker": "KXAVAXD-26FEB1510-T7.9999",
      "fair_prob_yes": 0.01,
      "market_mid_prob_yes": 0.01,
      "market_volume": 0.0,
      "spread_cents": 0.0,
      "confidence": 0.45,
      "rationale": "heuristic valuation fallback",
      "stale_after": "2026-02-15T15:05:26.276414Z"
    },
    {
      "ticker": "KXXLM-26FEB1510-B-0.1050000",
      "fair_prob_yes": 0.01,
      "market_mid_prob_yes": 0.01,
      "market_volume": 0.0,
      "spread_cents": 0.0,
      "confidence": 0.45,
      "rationale": "heuristic valuation fallback",
      "stale_after": "2026-02-15T15:05:26.276414Z"
    },
    {
      "ticker": "KXXRP-26FEB1510-B1.050",
      "fair_prob_yes": 0.01,
      "market_mid_prob_yes": 0.01,
      "market_volume": 0.0,
      "spread_cents": 0.0,
      "confidence": 0.45,
      "rationale": "heuristic valuation fallback",
      "stale_after": "2026-02-15T15:05:26.276415Z"
    },
    {
      "ticker": "KXLTCD-26FEB1510-T75.9999",
      "fair_prob_yes": 0.01,
      "market_mid_prob_yes": 0.01,
      "market_volume": 0.0,
      "spread_cents": 0.0,
      "confidence": 0.45,
      "rationale": "heuristic valuation fallback",
      "stale_after": "2026-02-15T15:05:26.276415Z"
    },
    {
      "ticker": "KXXLM-26FEB1510-B-0.1250001",
      "fair_prob_yes": 0.01,
      "market_mid_prob_yes": 0.01,
      "market_volume": 0.0,
      "spread_cents": 0.0,
      "confidence": 0.45,
      "rationale": "heuristic valuation fallback",
      "stale_after": "2026-02-15T15:05:26.276416Z"
    },
    {
      "ticker": "KXLTCD-26FEB1510-T64.9999",
      "fair_prob_yes": 0.01,
      "market_mid_prob_yes": 0.01,
      "market_volume": 0.0,
      "spread_cents": 0.0,
      "confidence": 0.45,
      "rationale": "heuristic valuation fallback",
      "stale_after": "2026-02-15T15:05:26.276417Z"
    },
    {
      "ticker": "KXLINK-26FEB1510-B12.50",
      "fair_prob_yes": 0.01,
      "market_mid_prob_yes": 0.01,
      "market_volume": 0.0,
      "spread_cents": 0.0,
      "confidence": 0.45,
      "rationale": "heuristic valuation fallback",
      "stale_after": "2026-02-15T15:05:26.276417Z"
    },
    {
      "ticker": "KXXRPD-26FEB1510-T1.63999",
      "fair_prob_yes": 0.01,
      "market_mid_prob_yes": 0.01,
      "market_volume": 0.0,
      "spread_cents": 0.0,
      "confidence": 0.45,
      "rationale": "heuristic valuation fallback",
      "stale_after": "2026-02-15T15:05:26.276418Z"
    },
    {
      "ticker": "KXLTC-26FEB1510-B58.5",
      "fair_prob_yes": 0.01,
      "market_mid_prob_yes": 0.01,
      "market_volume": 0.0,
      "spread_cents": 0.0,
      "confidence": 0.45,
      "rationale": "heuristic valuation fallback",
      "stale_after": "2026-02-15T15:05:26.276419Z"
    },
    {
      "ticker": "KXAVAX-26FEB1510-B2.25",
      "fair_prob_yes": 0.01,
      "market_mid_prob_yes": 0.01,
      "market_volume": 0.0,
      "spread_cents": 0.0,
      "confidence": 0.45,
      "rationale": "heuristic valuation fallback",
      "stale_after": "2026-02-15T15:05:26.276419Z"
    },
    {
      "ticker": "KXAVAXD-26FEB1510-T20.4999",
      "fair_prob_yes": 0.01,
      "market_mid_prob_yes": 0.01,
      "market_volume": 0.0,
      "spread_cents": 0.0,
      "confidence": 0.62,
      "rationale": "heuristic valuation fallback",
      "stale_after": "2026-02-15T14:55:27.280760Z"
    },
    {
      "ticker": "KXXLMD-26FEB1510-T-0.2700001",
      "fair_prob_yes": 0.01,
      "market_mid_prob_yes": 0.01,
      "market_volume": 0.0,
      "spread_cents": 0.0,
      "confidence": 0.45,
      "rationale": "heuristic valuation fallback",
      "stale_after": "2026-02-15T14:55:27.282275Z"
    },
    {
      "ticker": "KXXRPD-26FEB1510-T1.27999",
      "fair_prob_yes": 0.01,
      "market_mid_prob_yes": 0.01,
      "market_volume": 0.0,
      "spread_cents": 0.0,
      "confidence": 0.45,
      "rationale": "heuristic valuation fallback",
      "stale_after": "2026-02-15T14:55:27.281645Z"
    },
    {
      "ticker": "KXXLM-26FEB1510-B0.0949999",
      "fair_prob_yes": 0.01,
      "market_mid_prob_yes": 0.01,
      "market_volume": 0.0,
      "spread_cents": 0.0,
      "confidence": 0.45,
      "rationale": "heuristic valuation fallback",
      "stale_after": "2026-02-15T14:55:27.281628Z"
    },
    {
      "ticker": "KXXRPD-26FEB1510-T1.53999",
      "fair_prob_yes": 0.01,
      "market_mid_prob_yes": 0.01,
      "market_volume": 0.0,
      "spread_cents": 0.0,
      "confidence": 0.45,
      "rationale": "heuristic valuation fallback",
      "stale_after": "2026-02-15T14:55:27.281274Z"
    },
    {
      "ticker": "KXAVAX-26FEB1510-B-6.75",
      "fair_prob_yes": 0.01,
      "market_mid_prob_yes": 0.01,
      "market_volume": 0.0,
      "spread_cents": 0.0,
      "confidence": 0.62,
      "rationale": "heuristic valuation fallback",
      "stale_after": "2026-02-15T14:55:27.280783Z"
    },
    {
      "ticker": "KXLTC-26FEB1510-T91.9999",
      "fair_prob_yes": 0.01,
      "market_mid_prob_yes": 0.01,
      "market_volume": 0.0,
      "spread_cents": 0.0,
      "confidence": 0.45,
      "rationale": "heuristic valuation fallback",
      "stale_after": "2026-02-15T14:55:27.281997Z"
    },
    {
      "ticker": "KXLINKD-26FEB1510-T13.19999",
      "fair_prob_yes": 0.01,
      "market_mid_prob_yes": 0.01,
      "market_volume": 0.0,
      "spread_cents": 0.0,
      "confidence": 0.45,
      "rationale": "heuristic valuation fallback",
      "stale_after": "2026-02-15T14:55:27.281992Z"
    },
    {
      "ticker": "KXAVAX-26FEB1510-B23.25",
      "fair_prob_yes": 0.01,
      "market_mid_prob_yes": 0.01,
      "market_volume": 0.0,
      "spread_cents": 0.0,
      "confidence": 0.45,
      "rationale": "heuristic valuation fallback",
      "stale_after": "2026-02-15T14:55:27.281626Z"
    },
    {
      "ticker": "KXXRPD-26FEB1510-T1.19999",
      "fair_prob_yes": 0.01,
      "market_mid_prob_yes": 0.01,
      "market_volume": 0.0,
      "spread_cents": 0.0,
      "confidence": 0.45,
      "rationale": "heuristic valuation fallback",
      "stale_after": "2026-02-15T14:55:27.281639Z"
    },
    {
      "ticker": "KXAVAX-26FEB1510-B13.75",
      "fair_prob_yes": 0.01,
      "market_mid_prob_yes": 0.01,
      "market_volume": 0.0,
      "spread_cents": 0.0,
      "confidence": 0.45,
      "rationale": "heuristic valuation fallback",
      "stale_after": "2026-02-15T15:05:26.276586Z"
    },
    {
      "ticker": "KXXLMD-26FEB1510-T0.2699999",
      "fair_prob_yes": 0.01,
      "market_mid_prob_yes": 0.01,
      "market_volume": 0.0,
      "spread_cents": 0.0,
      "confidence": 0.45,
      "rationale": "heuristic valuation fallback",
      "stale_after": "2026-02-15T15:05:26.276587Z"
    },
    {
      "ticker": "KXXLM-26FEB1510-B0.1950000",
      "fair_prob_yes": 0.01,
      "market_mid_prob_yes": 0.01,
      "market_volume": 0.0,
      "spread_cents": 0.0,
      "confidence": 0.45,
      "rationale": "heuristic valuation fallback",
      "stale_after": "2026-02-15T15:05:26.276588Z"
    },
    {
      "ticker": "KXXRPD-26FEB1510-T1.37999",
      "fair_prob_yes": 0.01,
      "market_mid_prob_yes": 0.01,
      "market_volume": 0.0,
      "spread_cents": 0.0,
      "confidence": 0.45,
      "rationale": "heuristic valuation fallback",
      "stale_after": "2026-02-15T15:05:26.276588Z"
    },
    {
      "ticker": "KXXRP-26FEB1510-B1.650",
      "fair_prob_yes": 0.01,
      "market_mid_prob_yes": 0.01,
      "market_volume": 0.0,
      "spread_cents": 0.0,
      "confidence": 0.45,
      "rationale": "heuristic valuation fallback",
      "stale_after": "2026-02-15T15:05:26.276589Z"
    },
    {
      "ticker": "KXDOT-26FEB1510-B4.15",
      "fair_prob_yes": 0.01,
      "market_mid_prob_yes": 0.01,
      "market_volume": 0.0,
      "spread_cents": 0.0,
      "confidence": 0.45,
      "rationale": "heuristic valuation fallback",
      "stale_after": "2026-02-15T15:05:26.276590Z"
    },
    {
      "ticker": "KXXLMD-26FEB1510-T-0.2000001",
      "fair_prob_yes": 0.01,
      "market_mid_prob_yes": 0.01,
      "market_volume": 0.0,
      "spread_cents": 0.0,
      "confidence": 0.45,
      "rationale": "heuristic valuation fallback",
      "stale_after": "2026-02-15T15:05:26.276590Z"
    },
    {
      "ticker": "KXLTC-26FEB1510-B72.5",
      "fair_prob_yes": 0.01,
      "market_mid_prob_yes": 0.01,
      "market_volume": 0.0,
      "spread_cents": 0.0,
      "confidence": 0.45,
      "rationale": "heuristic valuation fallback",
      "stale_after": "2026-02-15T15:05:26.276591Z"
    },
    {
      "ticker": "KXBCHD-26FEB1510-T554.999",
      "fair_prob_yes": 0.01,
      "market_mid_prob_yes": 0.01,
      "market_volume": 0.0,
      "spread_cents": 0.0,
      "confidence": 0.45,
      "rationale": "heuristic valuation fallback",
      "stale_after": "2026-02-15T15:05:26.276592Z"
    },
    {
      "ticker": "KXXRPD-26FEB1510-T2.07999",
      "fair_prob_yes": 0.01,
      "market_mid_prob_yes": 0.01,
      "market_volume": 0.0,
      "spread_cents": 0.0,
      "confidence": 0.45,
      "rationale": "heuristic valuation fallback",
      "stale_after": "2026-02-15T15:05:26.276592Z"
    },
    {
      "ticker": "KXXRPD-26FEB1510-T1.81999",
      "fair_prob_yes": 0.01,
      "market_mid_prob_yes": 0.01,
      "market_volume": 0.0,
      "spread_cents": 0.0,
      "confidence": 0.45,
      "rationale": "heuristic valuation fallback",
      "stale_after": "2026-02-15T15:05:26.276593Z"
    },
    {
      "ticker": "KXDOTD-26FEB1510-T-2.60001",
      "fair_prob_yes": 0.01,
      "market_mid_prob_yes": 0.01,
      "market_volume": 0.0,
      "spread_cents": 0.0,
      "confidence": 0.45,
      "rationale": "heuristic valuation fallback",
      "stale_after": "2026-02-15T15:05:26.276593Z"
    },
    {
      "ticker": "KXLINK-26FEB1510-B8.50",
      "fair_prob_yes": 0.01,
      "market_mid_prob_yes": 0.01,
      "market_volume": 0.0,
      "spread_cents": 0.0,
      "confidence": 0.45,
      "rationale": "heuristic valuation fallback",
      "stale_after": "2026-02-15T15:05:26.276594Z"
    },
    {
      "ticker": "KXXLMD-26FEB1510-T0.1899999",
      "fair_prob_yes": 0.01,
      "market_mid_prob_yes": 0.01,
      "market_volume": 0.0,
      "spread_cents": 0.0,
      "confidence": 0.45,
      "rationale": "heuristic valuation fallback",
      "stale_after": "2026-02-15T15:05:26.276595Z"
    },
    {
      "ticker": "KXLINK-26FEB1510-B2.70",
      "fair_prob_yes": 0.01,
      "market_mid_prob_yes": 0.01,
      "market_volume": 0.0,
      "spread_cents": 0.0,
      "confidence": 0.45,
      "rationale": "heuristic valuation fallback",
      "stale_after": "2026-02-15T15:05:26.276595Z"
    },
    {
      "ticker": "KXDOTD-26FEB1510-T3.99999",
      "fair_prob_yes": 0.01,
      "market_mid_prob_yes": 0.01,
      "market_volume": 0.0,
      "spread_cents": 0.0,
      "confidence": 0.45,
      "rationale": "heuristic valuation fallback",
      "stale_after": "2026-02-15T15:05:26.276596Z"
    },
    {
      "ticker": "KXAVAXD-26FEB1510-T-6.5001",
      "fair_prob_yes": 0.01,
      "market_mid_prob_yes": 0.01,
      "market_volume": 0.0,
      "spread_cents": 0.0,
      "confidence": 0.45,
      "rationale": "heuristic valuation fallback",
      "stale_after": "2026-02-15T15:05:26.276597Z"
    },
    {
      "ticker": "KXLINK-26FEB1510-B6.50",
      "fair_prob_yes": 0.01,
      "market_mid_prob_yes": 0.01,
      "market_volume": 0.0,
      "spread_cents": 0.0,
      "confidence": 0.45,
      "rationale": "heuristic valuation fallback",
      "stale_after": "2026-02-15T15:05:26.276597Z"
    },
    {
      "ticker": "KXXRP-26FEB1510-B1.110",
      "fair_prob_yes": 0.01,
      "market_mid_prob_yes": 0.01,
      "market_volume": 0.0,
      "spread_cents": 0.0,
      "confidence": 0.45,
      "rationale": "heuristic valuation fallback",
      "stale_after": "2026-02-15T15:05:26.276598Z"
    },
    {
      "ticker": "KXDOTD-26FEB1510-T1.29999",
      "fair_prob_yes": 0.01,
      "market_mid_prob_yes": 0.01,
      "market_volume": 0.0,
      "spread_cents": 0.0,
      "confidence": 0.45,
      "rationale": "heuristic valuation fallback",
      "stale_after": "2026-02-15T15:05:26.276598Z"
    },
    {
      "ticker": "KXAVAXD-26FEB1510-T17.4999",
      "fair_prob_yes": 0.01,
      "market_mid_prob_yes": 0.01,
      "market_volume": 0.0,
      "spread_cents": 0.0,
      "confidence": 0.45,
      "rationale": "heuristic valuation fallback",
      "stale_after": "2026-02-15T15:05:26.276599Z"
    },
    {
      "ticker": "KXLTC-26FEB1510-B53.5",
      "fair_prob_yes": 0.01,
      "market_mid_prob_yes": 0.01,
      "market_volume": 0.0,
      "spread_cents": 0.0,
      "confidence": 0.45,
      "rationale": "heuristic valuation fallback",
      "stale_after": "2026-02-15T15:05:26.276600Z"
    },
    {
      "ticker": "KXXRP-26FEB1510-B1.470",
      "fair_prob_yes": 0.01,
      "market_mid_prob_yes": 0.01,
      "market_volume": 0.0,
      "spread_cents": 0.0,
      "confidence": 0.45,
      "rationale": "heuristic valuation fallback",
      "stale_after": "2026-02-15T14:55:27.282264Z"
    },
    {
      "ticker": "KXXLM-26FEB1510-B0.0849999",
      "fair_prob_yes": 0.01,
      "market_mid_prob_yes": 0.01,
      "market_volume": 0.0,
      "spread_cents": 0.0,
      "confidence": 0.45,
      "rationale": "heuristic valuation fallback",
      "stale_after": "2026-02-15T14:55:27.281977Z"
    },
    {
      "ticker": "KXAVAX-26FEB1510-B-8.75",
      "fair_prob_yes": 0.01,
      "market_mid_prob_yes": 0.01,
      "market_volume": 0.0,
      "spread_cents": 0.0,
      "confidence": 0.45,
      "rationale": "heuristic valuation fallback",
      "stale_after": "2026-02-15T14:55:27.281985Z"
    },
    {
      "ticker": "KXBCHD-26FEB1510-T474.999",
      "fair_prob_yes": 0.01,
      "market_mid_prob_yes": 0.01,
      "market_volume": 0.0,
      "spread_cents": 0.0,
      "confidence": 0.45,
      "rationale": "heuristic valuation fallback",
      "stale_after": "2026-02-15T15:05:26.276736Z"
    },
    {
      "ticker": "KXLTC-26FEB1510-B87.5",
      "fair_prob_yes": 0.01,
      "market_mid_prob_yes": 0.01,
      "market_volume": 0.0,
      "spread_cents": 0.0,
      "confidence": 0.45,
      "rationale": "heuristic valuation fallback",
      "stale_after": "2026-02-15T15:05:26.276737Z"
    },
    {
      "ticker": "KXXLM-26FEB1510-B0.2549999",
      "fair_prob_yes": 0.01,
      "market_mid_prob_yes": 0.01,
      "market_volume": 0.0,
      "spread_cents": 0.0,
      "confidence": 0.45,
      "rationale": "heuristic valuation fallback",
      "stale_after": "2026-02-15T15:05:26.276738Z"
    },
    {
      "ticker": "KXXRP-26FEB1510-B1.730",
      "fair_prob_yes": 0.01,
      "market_mid_prob_yes": 0.01,
      "market_volume": 0.0,
      "spread_cents": 0.0,
      "confidence": 0.45,
      "rationale": "heuristic valuation fallback",
      "stale_after": "2026-02-15T15:05:26.276739Z"
    },
    {
      "ticker": "KXLTCD-26FEB1510-T45.9999",
      "fair_prob_yes": 0.01,
      "market_mid_prob_yes": 0.01,
      "market_volume": 0.0,
      "spread_cents": 0.0,
      "confidence": 0.45,
      "rationale": "heuristic valuation fallback",
      "stale_after": "2026-02-15T15:05:26.276739Z"
    },
    {
      "ticker": "KXDOT-26FEB1510-B-1.15",
      "fair_prob_yes": 0.01,
      "market_mid_prob_yes": 0.01,
      "market_volume": 0.0,
      "spread_cents": 0.0,
      "confidence": 0.45,
      "rationale": "heuristic valuation fallback",
      "stale_after": "2026-02-15T15:05:26.276740Z"
    },
    {
      "ticker": "KXXLM-26FEB1510-B0.2950000",
      "fair_prob_yes": 0.01,
      "market_mid_prob_yes": 0.01,
      "market_volume": 0.0,
      "spread_cents": 0.0,
      "confidence": 0.45,
      "rationale": "heuristic valuation fallback",
      "stale_after": "2026-02-15T15:05:26.276741Z"
    },
    {
      "ticker": "KXAVAXD-26FEB1510-T27.4999",
      "fair_prob_yes": 0.01,
      "market_mid_prob_yes": 0.01,
      "market_volume": 0.0,
      "spread_cents": 0.0,
      "confidence": 0.45,
      "rationale": "heuristic valuation fallback",
      "stale_after": "2026-02-15T15:05:26.276741Z"
    },
    {
      "ticker": "KXAVAXD-26FEB1510-T-9.5001",
      "fair_prob_yes": 0.01,
      "market_mid_prob_yes": 0.01,
      "market_volume": 0.0,
      "spread_cents": 0.0,
      "confidence": 0.45,
      "rationale": "heuristic valuation fallback",
      "stale_after": "2026-02-15T15:05:26.276742Z"
    },
    {
      "ticker": "KXLINKD-26FEB1510-T1.99999",
      "fair_prob_yes": 0.01,
      "market_mid_prob_yes": 0.01,
      "market_volume": 0.0,
      "spread_cents": 0.0,
      "confidence": 0.45,
      "rationale": "heuristic valuation fallback",
      "stale_after": "2026-02-15T15:05:26.276742Z"
    },
    {
      "ticker": "KXXLMD-26FEB1510-T-0.2200001",
      "fair_prob_yes": 0.01,
      "market_mid_prob_yes": 0.01,
      "market_volume": 0.0,
      "spread_cents": 0.0,
      "confidence": 0.45,
      "rationale": "heuristic valuation fallback",
      "stale_after": "2026-02-15T15:05:26.276743Z"
    },
    {
      "ticker": "KXXRPD-26FEB1510-T0.67999",
      "fair_prob_yes": 0.01,
      "market_mid_prob_yes": 0.01,
      "market_volume": 0.0,
      "spread_cents": 0.0,
      "confidence": 0.45,
      "rationale": "heuristic valuation fallback",
      "stale_after": "2026-02-15T15:05:26.276744Z"
    },
    {
      "ticker": "KXDOT-26FEB1510-B3.95",
      "fair_prob_yes": 0.01,
      "market_mid_prob_yes": 0.01,
      "market_volume": 0.0,
      "spread_cents": 0.0,
      "confidence": 0.45,
      "rationale": "heuristic valuation fallback",
      "stale_after": "2026-02-15T15:05:26.276744Z"
    },
    {
      "ticker": "KXLTC-26FEB1510-B21.5",
      "fair_prob_yes": 0.01,
      "market_mid_prob_yes": 0.01,
      "market_volume": 0.0,
      "spread_cents": 0.0,
      "confidence": 0.45,
      "rationale": "heuristic valuation fallback",
      "stale_after": "2026-02-15T15:05:26.276745Z"
    },
    {
      "ticker": "KXLINKD-26FEB1510-T8.39999",
      "fair_prob_yes": 0.01,
      "market_mid_prob_yes": 0.01,
      "market_volume": 0.0,
      "spread_cents": 0.0,
      "confidence": 0.45,
      "rationale": "heuristic valuation fallback",
      "stale_after": "2026-02-15T15:05:26.276746Z"
    },
    {
      "ticker": "KXLINKD-26FEB1510-T4.39999",
      "fair_prob_yes": 0.01,
      "market_mid_prob_yes": 0.01,
      "market_volume": 0.0,
      "spread_cents": 0.0,
      "confidence": 0.45,
      "rationale": "heuristic valuation fallback",
      "stale_after": "2026-02-15T15:05:26.276746Z"
    },
    {
      "ticker": "KXXRP-26FEB1510-B0.710",
      "fair_prob_yes": 0.01,
      "market_mid_prob_yes": 0.01,
      "market_volume": 0.0,
      "spread_cents": 0.0,
      "confidence": 0.45,
      "rationale": "heuristic valuation fallback",
      "stale_after": "2026-02-15T15:05:26.276747Z"
    },
    {
      "ticker": "KXLTC-26FEB1510-B36.5",
      "fair_prob_yes": 0.01,
      "market_mid_prob_yes": 0.01,
      "market_volume": 0.0,
      "spread_cents": 0.0,
      "confidence": 0.45,
      "rationale": "heuristic valuation fallback",
      "stale_after": "2026-02-15T15:05:26.276747Z"
    },
    {
      "ticker": "KXLINKD-26FEB1510-T12.59999",
      "fair_prob_yes": 0.01,
      "market_mid_prob_yes": 0.01,
      "market_volume": 0.0,
      "spread_cents": 0.0,
      "confidence": 0.45,
      "rationale": "heuristic valuation fallback",
      "stale_after": "2026-02-15T15:05:26.276748Z"
    }
  ],
  "candidates": [],
  "allocations": [],
  "executions": []
}